chemlog_extra/__init__.py
chemlog_extra/alg_classification/__init__.py
chemlog_extra/alg_classification/by_element_classification.py
chemlog_extra-1.0.0.dist-info/licenses/LICENSE
chemlog_extra-1.0.0.dist-info/METADATA
chemlog_extra-1.0.0.dist-info/WHEEL
chemlog_extra-1.0.0.dist-info/top_level.txt
chemlog_extra-1.0.0.dist-info/RECORD
