Metadata-Version: 2.4
Name: chemlog-extra
Version: 1.0.0
Summary: Extension of ChemLog to a broad range of ChEBI classes
Author-email: sfluegel05 <simon.fluegel@uni-osnabrueck.de>
License-File: LICENSE
Requires-Dist: chemlog
Dynamic: license-file
